{
    "frames": {
        "redseven": { "frame": { "x": 1026, "y": 0, "w": 512, "h": 512 }, "rotated": false, "trimmed": false, "spriteSourceSize": { "x": 0, "y": 0, "w": 512, "h": 512 }, "sourceSize": { "w": 512, "h": 512 } },
        "plum": { "frame": { "x": 0, "y": 513, "w": 512, "h": 512 }, "rotated": false, "trimmed": false, "spriteSourceSize": { "x": 0, "y": 0, "w": 512, "h": 512 }, "sourceSize": { "w": 512, "h": 512 } },
        "redbar": { "frame": { "x": 513, "y": 0, "w": 512, "h": 512 }, "rotated": false, "trimmed": false, "spriteSourceSize": { "x": 0, "y": 0, "w": 512, "h": 512 }, "sourceSize": { "w": 512, "h": 512 } },
        "bell": { "frame": { "x": 513, "y": 513, "w": 512, "h": 512 }, "rotated": false, "trimmed": false, "spriteSourceSize": { "x": 0, "y": 0, "w": 512, "h": 512 }, "sourceSize": { "w": 512, "h": 512 } },
        "goldbar": { "frame": { "x": 0, "y": 1026, "w": 512, "h": 512 }, "rotated": false, "trimmed": false, "spriteSourceSize": { "x": 0, "y": 0, "w": 512, "h": 512 }, "sourceSize": { "w": 512, "h": 512 } },
        "greenbar": { "frame": { "x": 513, "y": 1026, "w": 512, "h": 512 }, "rotated": false, "trimmed": false, "spriteSourceSize": { "x": 0, "y": 0, "w": 512, "h": 512 }, "sourceSize": { "w": 512, "h": 512 } },
        "big_money_slots": { "frame": { "x": 609, "y": 1539, "w": 600, "h": 449 }, "rotated": false, "trimmed": false, "spriteSourceSize": { "x": 0, "y": 0, "w": 600, "h": 449 }, "sourceSize": { "w": 600, "h": 449 } },
        "lemon": { "frame": { "x": 1026, "y": 513, "w": 512, "h": 512 }, "rotated": false, "trimmed": false, "spriteSourceSize": { "x": 0, "y": 0, "w": 512, "h": 512 }, "sourceSize": { "w": 512, "h": 512 } },
        "grape": { "frame": { "x": 1026, "y": 1026, "w": 512, "h": 512 }, "rotated": false, "trimmed": false, "spriteSourceSize": { "x": 0, "y": 0, "w": 512, "h": 512 }, "sourceSize": { "w": 512, "h": 512 } },
        "slot_machine_flame": { "frame": { "x": 0, "y": 1539, "w": 608, "h": 500 }, "rotated": false, "trimmed": false, "spriteSourceSize": { "x": 0, "y": 0, "w": 608, "h": 500 }, "sourceSize": { "w": 608, "h": 500 } },
        "CasinoSlotsSliderBackground": { "frame": { "x": 0, "y": 2040, "w": 1680, "h": 470 }, "rotated": false, "trimmed": false, "spriteSourceSize": { "x": 0, "y": 0, "w": 1680, "h": 470 }, "sourceSize": { "w": 1680, "h": 470 } },
        "spin_button": { "frame": { "x": 0, "y": 0, "w": 512, "h": 512 }, "rotated": false, "trimmed": false, "spriteSourceSize": { "x": 0, "y": 0, "w": 512, "h": 512 }, "sourceSize": { "w": 512, "h": 512 } }
    },
    "meta": {
        "app": "https://www.leshylabs.com/apps/sstool/",
        "version": "Leshy SpriteSheet Tool v0.8.4",
        "image": "slots.png",
        "size": { "w": 1680, "h": 2510 },
        "scale": 1
    }
}
